cdr_tools/__init__.py
cdr_tools/__main__.py
cdr_tools/cdr_tools.py
cdr_tools/cdr_utils.py
cdr_tools/settings.py
cdr_tools/test_extract_qa.py
eea_cdrtools-0.5.2.dist-info/LICENSE.txt
eea_cdrtools-0.5.2.dist-info/METADATA
eea_cdrtools-0.5.2.dist-info/WHEEL
eea_cdrtools-0.5.2.dist-info/entry_points.txt
eea_cdrtools-0.5.2.dist-info/top_level.txt
eea_cdrtools-0.5.2.dist-info/RECORD
