Metadata-Version: 2.1
Name: eea-cdrtools
Version: 0.5.2
Summary: A set of tool to interact with EEA Reportnet2 (CDR) API. It includes CLI tools and supporting library
Author-email: Luca Liberti <libertil@gmail.com>
Project-URL: Homepage, https://github.com/libertil/eea-cdrtools
Keywords: EEA,cli,reportnet
Classifier: License :: OSI Approved :: GNU Affero General Public License v3
Classifier: Programming Language :: Python
Classifier: Programming Language :: Python :: 3
Requires-Python: >=3.8
License-File: LICENSE.txt
Requires-Dist: certifi >=2022.6.15
Requires-Dist: charset-normalizer >=2.1.0
Requires-Dist: click >=8.1.3
Requires-Dist: idna >=3.3
Requires-Dist: lxml >=4.9.1
Requires-Dist: requests >=2.28.1
Requires-Dist: tabulate >=0.8.10
Requires-Dist: urllib3 >=1.26.9
Provides-Extra: dev
Requires-Dist: black ; extra == 'dev'
Requires-Dist: pip-tools ; extra == 'dev'
Requires-Dist: pytest ; extra == 'dev'
